README.md
setup.py
jkcli/__init__.py
jkcli/__main__.py
jkcli/main.py
jkcli/version.py
jkcli.egg-info/PKG-INFO
jkcli.egg-info/SOURCES.txt
jkcli.egg-info/dependency_links.txt
jkcli.egg-info/top_level.txt